setup.py
blockstack_profiles/__init__.py
blockstack_profiles/legacy_format.py
blockstack_profiles/person.py
blockstack_profiles/token_signing.py
blockstack_profiles/token_verifying.py
blockstack_profiles/zone_file_format.py
blockstack_profiles.egg-info/PKG-INFO
blockstack_profiles.egg-info/SOURCES.txt
blockstack_profiles.egg-info/dependency_links.txt
blockstack_profiles.egg-info/not-zip-safe
blockstack_profiles.egg-info/requires.txt
blockstack_profiles.egg-info/top_level.txt