Metadata-Version: 1.1
Name: blockstack-profiles
Version: 0.14.1
Summary: Library for blockstack profile generation and validation
Home-page: https://github.com/blockstack/blockstack-profiles-py
Author: Blockstack Developers
Author-email: hello@onename.com
License: MIT
Keywords: bitcoin blockchain blockstack profile schema
Platform: UNKNOWN
Classifier: Intended Audience :: Developers
Classifier: License :: OSI Approved :: MIT License
Classifier: Operating System :: OS Independent
Classifier: Programming Language :: Python
Classifier: Topic :: Internet
Classifier: Topic :: Security :: Cryptography
Classifier: Topic :: Software Development :: Libraries :: Python Modules
